{
  "poems": [
    {
      "id": 2,
      "title": "My Pickle",
      "content": "...may my pickle stroll about hungryand fearless and thirsty and suppleand even if it's sunday may it be wrongfor whenever gherkins are green they are not young and may my sweet and sour do nothing usefullyand love yourself so more than pickle-juiceythere's never been quite such a fool who could failpulling all the sky over him with one bite.",
      "author": "Jon Glass"
    },
    {
      "title": "wervwerv",
      "content": "vervwerv",
      "author": "vwervwe",
      "id": 3
    },
    {
      "title": "wervwerv",
      "content": "vervwerv",
      "author": "vwervwe",
      "id": 4
    },
    {
      "title": "wervwerv",
      "content": "vervwerv",
      "author": "vwervwe",
      "id": 5
    },
    {
      "title": "ercwer",
      "content": "ewrvwerv",
      "author": "vwervwer",
      "id": 6
    },
    {
      "title": "wqefqwe",
      "content": "fffff",
      "author": "wfeqw",
      "id": 7
    }
  ]
}